<?xml version="1.0" encoding="UTF-8"?>
<person xmlns="http://www.tei-c.org/ns/1.0" xml:id="pers_resource_000001">
    <idno type="gnd"/>
    <persName type="reg"><surname/><forename/><genName/><roleName>Tuteur</roleName></persName><gender value="M">male</gender>
    <floruit><date from="1755" to="1755"/></floruit>
    <note type="bio" resp="SG">Es handelt sich um den nicht weiter identifizierten Erzieher von <rs type="person" key="pers_DE-588-1203086830">Theodor Gernler (1722-1801)</rs>.</note>
    <note type="internal"/><bibl/>
</person>