<?xml version="1.0" encoding="UTF-8"?><?xml-stylesheet type="text/css" href="Einzeldaten_test.css"?>
<place xml:id="place_VER-passya" xmlns="http://www.tei-c.org/ns/1.0"><placeName xml:lang="de"
        type="Verwaltungseinheit">Passy</placeName><location><country>FR</country><geo
            decls="lon_wgs84_dd">2.2769</geo><geo decls="lat_wgs84_dd"
        >48.8637</geo></location><placeName xml:lang="en"/><placeName xml:lang="fr"/><placeName
        xml:lang="la"/><ptr type="wikipedia" target="https://de.wikipedia.org/wiki/Passy_(Paris)"
        /><ptr type="geonames" target="https://www.geonames.org/2988394/paris-16-passy.html"/><note
        hand="intern">Ehemalige Gemeinde, heute Teil des 16. Arrondissements von
    Paris.</note></place>